termonal_style/__init__.py
termonal_style/styles.py
termonal_style-1.1.dist-info/METADATA
termonal_style-1.1.dist-info/WHEEL
termonal_style-1.1.dist-info/top_level.txt
termonal_style-1.1.dist-info/RECORD
