Metadata-Version: 2.4
Name: termonal_style
Version: 1.1
Summary: A simple library for terminal text styling and colors.
Author-email: GFardad <greengame986@gmail.com>
Project-URL: Homepage, https://github.com/GFardad/Termonal_style
